{
    "@schema": "https://raw.githubusercontent.com/slicer/slicer/master/Modules/Loadable/Markups/Resources/Schema/markups-schema-v1.0.3.json#",
    "markups": [
        {
            "type": "Fiducial",
            "coordinateSystem": "LPS",
            "coordinateUnits": "mm",
            "locked": false,
            "fixedNumberOfControlPoints": false,
            "labelFormat": "%N-%d",
            "lastUsedControlPointNumber": 9,
            "controlPoints": [
                {
                    "id": "1",
                    "label": "anus",
                    "description": "",
                    "associatedNodeID": "vtkMRMLScalarVolumeNode1",
                    "position": [-5.580037500000001, 185.23232516921263, -660.6582067336884],
                    "orientation": [-1.0, -0.0, -0.0, -0.0, -1.0, -0.0, 0.0, 0.0, 1.0],
                    "selected": true,
                    "locked": false,
                    "visibility": true,
                    "positionStatus": "defined"
                },
                {
                    "id": "2",
                    "label": "coccyx inferior",
                    "description": "",
                    "associatedNodeID": "vtkMRMLScalarVolumeNode1",
                    "position": [-5.580037500000001, 200.1616912374214, -597.4279504448043],
                    "orientation": [-1.0, -0.0, -0.0, -0.0, -1.0, -0.0, 0.0, 0.0, 1.0],
                    "selected": true,
                    "locked": false,
                    "visibility": true,
                    "positionStatus": "defined"
                },
                {
                    "id": "3",
                    "label": "obstetrical symph top",
                    "description": "",
                    "associatedNodeID": "vtkMRMLScalarVolumeNode1",
                    "position": [-5.580037500000001, 83.10746320212735, -614.2068480767282],
                    "orientation": [-1.0, -0.0, -0.0, -0.0, -1.0, -0.0, 0.0, 0.0, 1.0],
                    "selected": true,
                    "locked": false,
                    "visibility": true,
                    "positionStatus": "defined"
                },
                {
                    "id": "4",
                    "label": "symph inferior",
                    "description": "",
                    "associatedNodeID": "vtkMRMLScalarVolumeNode1",
                    "position": [-5.580037500000001, 105.75540580610122, -632.5558706052955],
                    "orientation": [-1.0, -0.0, -0.0, -0.0, -1.0, -0.0, 0.0, 0.0, 1.0],
                    "selected": true,
                    "locked": false,
                    "visibility": true,
                    "positionStatus": "defined"
                },
                {
                    "id": "5",
                    "label": "symph superior",
                    "description": "",
                    "associatedNodeID": "vtkMRMLScalarVolumeNode1",
                    "position": [-5.580037500000001, 75.45757466767755, -617.1874055350805],
                    "orientation": [-1.0, -0.0, -0.0, -0.0, -1.0, -0.0, 0.0, 0.0, 1.0],
                    "selected": true,
                    "locked": false,
                    "visibility": true,
                    "positionStatus": "defined"
                },
                {
                    "id": "6",
                    "label": "urethra",
                    "description": "",
                    "associatedNodeID": "vtkMRMLScalarVolumeNode1",
                    "position": [-5.580037500000001, 127.71035590640822, -648.8025336795226],
                    "orientation": [-1.0, -0.0, -0.0, -0.0, -1.0, -0.0, 0.0, 0.0, 1.0],
                    "selected": true,
                    "locked": false,
                    "visibility": true,
                    "positionStatus": "defined"
                },
                {
                    "id": "7",
                    "label": "vertebra caudo-cranial 1",
                    "description": "",
                    "associatedNodeID": "vtkMRMLScalarVolumeNode1",
                    "position": [-5.580037500000001, 214.54707078516532, -561.2458919267572],
                    "orientation": [-1.0, -0.0, -0.0, -0.0, -1.0, -0.0, 0.0, 0.0, 1.0],
                    "selected": true,
                    "locked": false,
                    "visibility": true,
                    "positionStatus": "defined"
                },
                {
                    "id": "8",
                    "label": "vertebra caudo-cranial 2",
                    "description": "",
                    "associatedNodeID": "vtkMRMLScalarVolumeNode1",
                    "position": [-5.580037500000001, 209.58991372998298, -542.4608757176452],
                    "orientation": [-1.0, -0.0, -0.0, -0.0, -1.0, -0.0, 0.0, 0.0, 1.0],
                    "selected": true,
                    "locked": false,
                    "visibility": true,
                    "positionStatus": "defined"
                },
                {
                    "id": "9",
                    "label": "vertebra caudo-cranial 3",
                    "description": "",
                    "associatedNodeID": "vtkMRMLScalarVolumeNode1",
                    "position": [-5.580037500000001, 198.1101816021923, -529.1548225695242],
                    "orientation": [-1.0, -0.0, -0.0, -0.0, -1.0, -0.0, 0.0, 0.0, 1.0],
                    "selected": true,
                    "locked": false,
                    "visibility": true,
                    "positionStatus": "defined"
                }
            ],
            "measurements": [],
            "display": {
                "visibility": true,
                "opacity": 1.0,
                "color": [0.4, 1.0, 1.0],
                "selectedColor": [1.0, 0.5000076295109483, 0.5000076295109483],
                "activeColor": [0.4, 1.0, 0.0],
                "propertiesLabelVisibility": false,
                "pointLabelsVisibility": true,
                "textScale": 3.0,
                "glyphType": "StarBurst2D",
                "glyphScale": 3.0,
                "glyphSize": 5.0,
                "useGlyphScale": true,
                "sliceProjection": false,
                "sliceProjectionUseFiducialColor": true,
                "sliceProjectionOutlinedBehindSlicePlane": false,
                "sliceProjectionColor": [1.0, 1.0, 1.0],
                "sliceProjectionOpacity": 0.6,
                "lineThickness": 0.2,
                "lineColorFadingStart": 1.0,
                "lineColorFadingEnd": 10.0,
                "lineColorFadingSaturation": 1.0,
                "lineColorFadingHueOffset": 0.0,
                "handlesInteractive": false,
                "translationHandleVisibility": true,
                "rotationHandleVisibility": true,
                "scaleHandleVisibility": false,
                "interactionHandleScale": 3.3000000000000003,
                "snapMode": "toVisibleSurface"
            }
        }
    ]
}